zsl/__init__.py
zsl/__main__.py
zsl/_state.py
zsl/constants.py
zsl/errors.py
zsl/gearman.py
zsl/version.py
zsl/application/__init__.py
zsl/application/error_handler.py
zsl/application/initialization_context.py
zsl/application/service_application.py
zsl/application/containers/__init__.py
zsl/application/containers/celery_container.py
zsl/application/containers/container.py
zsl/application/containers/core_container.py
zsl/application/containers/gearman_container.py
zsl/application/containers/web_container.py
zsl/application/initializers/__init__.py
zsl/application/initializers/library_initializer.py
zsl/application/initializers/service_initializer.py
zsl/application/initializers/unittest_initializer.py
zsl/application/modules/__init__.py
zsl/application/modules/alchemy_module.py
zsl/application/modules/cache_module.py
zsl/application/modules/celery_module.py
zsl/application/modules/cli_module.py
zsl/application/modules/context_module.py
zsl/application/modules/error_handler_module.py
zsl/application/modules/gearman_module.py
zsl/application/modules/logger_module.py
zsl/application/modules/task_router.py
zsl/application/modules/web/__init__.py
zsl/application/modules/web/configuration.py
zsl/application/modules/web/cors.py
zsl/application/modules/web/web_context_module.py
zsl/cache/__init__.py
zsl/cache/cache_module.py
zsl/cache/id_helper.py
zsl/cache/redis_cache_module.py
zsl/cache/redis_id_helper.py
zsl/configuration/__init__.py
zsl/contrib/__init__.py
zsl/contrib/alembic/__init__.py
zsl/contrib/alembic/alembic_config.py
zsl/contrib/alembic/alembic_module.py
zsl/contrib/sentry/__init__.py
zsl/contrib/sentry/sentry_config.py
zsl/contrib/sentry/sentry_module.py
zsl/db/__init__.py
zsl/db/helpers/__init__.py
zsl/db/helpers/nested.py
zsl/db/helpers/pagination.py
zsl/db/helpers/query_filter.py
zsl/db/helpers/query_helper.py
zsl/db/helpers/sorter.py
zsl/db/model/__init__.py
zsl/db/model/app_model.py
zsl/db/model/app_model_json_decoder.py
zsl-1.7.5.dist-info/LICENSE
zsl-1.7.5.dist-info/METADATA
zsl-1.7.5.dist-info/WHEEL
zsl-1.7.5.dist-info/top_level.txt
zsl-1.7.5.dist-info/RECORD
