Metadata-Version: 2.1
Name: zsl
Version: 1.7.5
Summary: zsl application framework for web based services
Home-page: https://github.com/AtteqCom/zsl
Author: Atteq s.r.o.
Author-email: open.source@atteq.com
License: MIT
Platform: UNKNOWN
Classifier: Development Status :: 3 - Alpha
Classifier: Programming Language :: Python :: 3.8
Classifier: Programming Language :: Python :: 3.9
Classifier: Programming Language :: Python :: 3.10
Classifier: Programming Language :: Python :: 3.11
Classifier: Operating System :: OS Independent
Classifier: Topic :: Software Development :: Libraries :: Application Frameworks
License-File: LICENSE
Requires-Dist: SQLAlchemy (>=1.3)
Requires-Dist: flask (>=2.3.3)
Requires-Dist: injector (==0.12.1)
Requires-Dist: python3-gearman
Requires-Dist: requests (>=2.22)
Requires-Dist: typing (>=3.7)
Provides-Extra: alembic
Requires-Dist: alembic ; extra == 'alembic'
Provides-Extra: celery
Requires-Dist: celery (>=5.3.4) ; extra == 'celery'
Requires-Dist: zsl-client ; extra == 'celery'
Provides-Extra: cli
Requires-Dist: bpython ; extra == 'cli'
Requires-Dist: click (>=7.0) ; extra == 'cli'
Provides-Extra: documentation
Requires-Dist: alembic ; extra == 'documentation'
Requires-Dist: recommonmark ; extra == 'documentation'
Requires-Dist: sphinx ; extra == 'documentation'
Requires-Dist: sphinx-rtd-theme ; extra == 'documentation'
Provides-Extra: gearman
Requires-Dist: python3-gearman ; extra == 'gearman'
Requires-Dist: zsl-client ; extra == 'gearman'
Provides-Extra: redis
Requires-Dist: redis (>=3.2.0) ; extra == 'redis'
Provides-Extra: sentry
Requires-Dist: sentry-sdk[flask] ; extra == 'sentry'
